thu_rsvp_dataset/__init__.py
thu_rsvp_dataset/files.py
thu_rsvp_dataset/filter.py
thu_rsvp_dataset/thu.py
thu_rsvp_dataset/utils.py
thu_rsvp_dataset/worker.py
thu_rsvp_dataset-1.1.0.dist-info/LICENSE.txt
thu_rsvp_dataset-1.1.0.dist-info/METADATA
thu_rsvp_dataset-1.1.0.dist-info/WHEEL
thu_rsvp_dataset-1.1.0.dist-info/top_level.txt
thu_rsvp_dataset-1.1.0.dist-info/RECORD
