Metadata-Version: 2.1
Name: thu-rsvp-dataset
Version: 1.1.0
Summary: Tsinghua University RSVP Benchmark Dataset
Home-page: https://github.com/nik-sm/thu-rsvp-dataset.git
Author: Niklas Smedemark-Margulies
Author-email: niklas.sm+github@gmail.com
License: MIT
Platform: UNKNOWN
Requires-Python: >=3.7
Requires-Dist: loguru
Requires-Dist: numpy
Requires-Dist: requests
Requires-Dist: scipy
Requires-Dist: tqdm
